ligo_synthetic_pe/__init__.py
ligo_synthetic_pe/cli.py
ligo_synthetic_pe/fisher.py
ligo_synthetic_pe/gw.py
ligo_synthetic_pe/spin_samplers.py
ligo_synthetic_pe/synthetic_pe.py
ligo_synthetic_pe/utils.py
ligo_synthetic_pe/EM_Bright/__init__.py
ligo_synthetic_pe/EM_Bright/effectiveFisher.py
ligo_synthetic_pe/EM_Bright/getEllipsoidSamples.py
ligo_synthetic_pe-2.0.0.dist-info/LICENSE
ligo_synthetic_pe-2.0.0.dist-info/METADATA
ligo_synthetic_pe-2.0.0.dist-info/WHEEL
ligo_synthetic_pe-2.0.0.dist-info/entry_points.txt
ligo_synthetic_pe-2.0.0.dist-info/top_level.txt
ligo_synthetic_pe-2.0.0.dist-info/RECORD
